{
  "Comics": {
    "Browser": "C:\\Program Files\\Mozilla Firefox\\firefox.exe",
    "NetworkShare": "",
    "Website": [
      {
        "Name": "https://politicalcartoons.com/cartoonist/alla-and-chavdar/",
        "Type": "politicalcartoons"
      },
      {
        "Name": "https://politicalcartoons.com/cartoonist/angel-boligan/",
        "Type": "politicalcartoons"
      },
      {
        "Name": "https://politicalcartoons.com/cartoonist/bart-van-leeuwen/",
        "Type": "politicalcartoons"
      },
      {
        "Name": "https://politicalcartoons.com/cartoonist/bill-day/",
        "Type": "politicalcartoons"
      },
      {
        "Name": "https://politicalcartoons.com/cartoonist/bob-englehart/",
        "Type": "politicalcartoons"
      },
      {
        "Name": "https://politicalcartoons.com/cartoonist/bruce-plante/",
        "Type": "politicalcartoons"
      },
      {
        "Name": "https://politicalcartoons.com/cartoonist/daryl-cagle/",
        "Type": "politicalcartoons"
      },
      {
        "Name": "https://politicalcartoons.com/cartoonist/dave-granlund/",
        "Type": "politicalcartoons"
      },
      {
        "Name": "https://politicalcartoons.com/cartoonist/emad-hajjaj/",
        "Type": "politicalcartoons"
      },
      {
        "Name": "https://politicalcartoons.com/cartoonist/gatis-sluka/",
        "Type": "politicalcartoons"
      },
      {
        "Name": "https://politicalcartoons.com/cartoonist/guy-parsons/",
        "Type": "politicalcartoons"
      },
      {
        "Name": "https://politicalcartoons.com/cartoonist/jimmy-margulies/",
        "Type": "politicalcartoons"
      },
      {
        "Name": "https://politicalcartoons.com/cartoonist/joep-bertrams/",
        "Type": "politicalcartoons"
      },
      {
        "Name": "https://politicalcartoons.com/cartoonist/joe-heller/",
        "Type": "politicalcartoons"
      },
      {
        "Name": "https://politicalcartoons.com/cartoonist/john-cole/",
        "Type": "politicalcartoons"
      },
      {
        "Name": "https://politicalcartoons.com/cartoonist/john-darkow/",
        "Type": "politicalcartoons"
      },
      {
        "Name": "https://politicalcartoons.com/cartoonist/kevin-siers/",
        "Type": "politicalcartoons"
      },
      {
        "Name": "https://politicalcartoons.com/cartoonist/luojie/",
        "Type": "politicalcartoons"
      },
      {
        "Name": "https://politicalcartoons.com/cartoonist/michael-kountouris/",
        "Type": "politicalcartoons"
      },
      {
        "Name": "https://politicalcartoons.com/cartoonist/monte-wolverton/",
        "Type": "politicalcartoons"
      },
      {
        "Name": "https://politicalcartoons.com/cartoonist/nikola-listes/",
        "Type": "politicalcartoons"
      },
      {
        "Name": "https://politicalcartoons.com/cartoonist/paresh-nath/",
        "Type": "politicalcartoons"
      },
      {
        "Name": "https://politicalcartoons.com/cartoonist/pat-bagley/",
        "Type": "politicalcartoons"
      },
      {
        "Name": "https://politicalcartoons.com/cartoonist/pat-byrnes/",
        "Type": "politicalcartoons"
      },
      {
        "Name": "https://politicalcartoons.com/cartoonist/petar-pismestrovic/",
        "Type": "politicalcartoons"
      },
      {
        "Name": "https://politicalcartoons.com/cartoonist/rainer-hachfeld/",
        "Type": "politicalcartoons"
      },
      {
        "Name": "https://politicalcartoons.com/cartoonist/randall-enos/",
        "Type": "politicalcartoons"
      },
      {
        "Name": "https://politicalcartoons.com/cartoonist/rick-mckee/",
        "Type": "politicalcartoons"
      },
      {
        "Name": "https://politicalcartoons.com/cartoonist/schot/",
        "Type": "politicalcartoons"
      },
      {
        "Name": "https://politicalcartoons.com/cartoonist/steve-sack/",
        "Type": "politicalcartoons"
      },
      {
        "Name": "https://politicalcartoons.com/cartoonist/taylor-jones/",
        "Type": "politicalcartoons"
      },
      {
        "Name": "https://xkcd.com/",
        "Type": "xkcd"
      }
    ]
  }
}